broadcastlogging.py
setup.py
broadcast_logging.egg-info/PKG-INFO
broadcast_logging.egg-info/SOURCES.txt
broadcast_logging.egg-info/dependency_links.txt
broadcast_logging.egg-info/top_level.txt