Metadata-Version: 1.0
Name: broadcast-logging
Version: 0.1
Summary: A Python logging system handler which broadcasts log messages and a matching receiver executable.
Home-page: https://github.com/languitar/broadcast-logging
Author: Johannes Wienke
Author-email: languitar@semipol.de
License: LPGLv3+
Platform: UNKNOWN
